smartquadtree.pyd
smartquadtree-1.0.dist-info/DESCRIPTION.rst
smartquadtree-1.0.dist-info/METADATA
smartquadtree-1.0.dist-info/metadata.json
smartquadtree-1.0.dist-info/RECORD
smartquadtree-1.0.dist-info/top_level.txt
smartquadtree-1.0.dist-info/WHEEL
