Metadata-Version: 1.0
Name: smartquadtree
Version: 1.0
Summary: Implementation of quadtrees for moving objects
Home-page: https://github.com/xoolive/quadtree
Author: Xavier Olive
Author-email: xavier@xoolive.org
License: MIT
Platform: UNKNOWN
